ambient_gen/__init__.py
ambient_gen/__main__.py
ambient_gen/soundfont_manager.py
ambient_gen/soundfonts.tar.xz
ambient_gen/tui.py
ambient_gen-1.2.0.dist-info/licenses/LICENSE
ambient_gen-1.2.0.dist-info/licenses/LICENSES.md
ambient_gen-1.2.0.dist-info/METADATA
ambient_gen-1.2.0.dist-info/WHEEL
ambient_gen-1.2.0.dist-info/entry_points.txt
ambient_gen-1.2.0.dist-info/top_level.txt
ambient_gen-1.2.0.dist-info/RECORD
