Metadata-Version: 2.4
Name: ambient-gen
Version: 1.2.0
Summary: Create lush, generative ambient music with spacey textures
Author-email: Beowulf Audio <hello@beowulfaudio.dev>
License: MIT
Project-URL: Homepage, https://github.com/beowulf-audio/ambient-gen-tui
Project-URL: Repository, https://github.com/beowulf-audio/ambient-gen-tui
Project-URL: Issues, https://github.com/beowulf-audio/ambient-gen-tui/issues
Keywords: music,ambient,generative,midi,japanese,hirajoshi,soundfont,synthesis,tui
Classifier: Development Status :: 5 - Production/Stable
Classifier: Intended Audience :: End Users/Desktop
Classifier: Topic :: Multimedia :: Sound/Audio :: MIDI
Classifier: Topic :: Multimedia :: Sound/Audio :: Sound Synthesis
Classifier: Programming Language :: Python :: 3
Classifier: Programming Language :: Python :: 3.8
Classifier: Programming Language :: Python :: 3.9
Classifier: Programming Language :: Python :: 3.10
Classifier: Programming Language :: Python :: 3.11
Classifier: Programming Language :: Python :: 3.12
Classifier: Environment :: Console
Classifier: Operating System :: OS Independent
Requires-Python: >=3.8
License-File: LICENSE
License-File: LICENSES.md
Requires-Dist: mido>=1.2.10
Requires-Dist: textual>=0.47.0
Requires-Dist: rich>=13.0.0
Requires-Dist: tinysoundfont>=0.3.7
Requires-Dist: static-ffmpeg>=2.5
Requires-Dist: numpy>=1.20.0
Provides-Extra: dev
Requires-Dist: pytest>=7.0; extra == "dev"
Requires-Dist: black>=22.0; extra == "dev"
Requires-Dist: flake8>=4.0; extra == "dev"
Dynamic: license-file
